astrow_images/__init__.py
astrow_images/effects.py
astrow_images/gif_effects.py
astrow_images/memes.py
astrow_images/utils.py
astrow_images-2.0.dist-info/LICENSE
astrow_images-2.0.dist-info/METADATA
astrow_images-2.0.dist-info/WHEEL
astrow_images-2.0.dist-info/top_level.txt
astrow_images-2.0.dist-info/RECORD
