Metadata-Version: 2.1
Name: astrow-images
Version: 2.0
Summary: An image manipulation module for Astrow.
Home-page: https://github.com/kristenkamouh/astrow-images.git
Author: Kamouh_
License: MIT
Keywords: discord.py,meme,discord,image-gen
Platform: UNKNOWN
Requires-Python: >=3.5.3
License-File: LICENSE
Requires-Dist: pillow (>=8.1.2)
Requires-Dist: wand (>=0.6.6)
Requires-Dist: numpy (>=1.21.1)
